LICENSE
README.md
pyproject.toml
setup.cfg
setup.py
src/suggest_five/__init__.py
src/suggest_five/__main__.py
src/suggest_five/benchmark_performance.py
src/suggest_five/game.py
src/suggest_five/guess_results.py
src/suggest_five/io.py
src/suggest_five/naive_guesser.py
src/suggest_five/ui.py
src/suggest_five/util.py
src/suggest_five.egg-info/PKG-INFO
src/suggest_five.egg-info/SOURCES.txt
src/suggest_five.egg-info/dependency_links.txt
src/suggest_five.egg-info/entry_points.txt
src/suggest_five.egg-info/top_level.txt
src/suggest_five.egg-info/zip-safe